{
	"pages": [ //pages数组中第一项表示应用启动页，参考：https://uniapp.dcloud.io/collocation/pages
		{
			"path": "pages/index/index",
			"style": {

			}
		}, {
			"path": "pages/index/test",
			"style": {

			}
		}
	],
	"tabBar": {
		"color": "#666666",
		"selectedColor": "#ff0000",
		"backgroundColor": "#ffffff",
		"borderStyle": "white",
		"list": [{
				"pagePath": "pages/home/home",
				"text": "首页",
				"iconPath": "static/img/home.png",
				"selectedIconPath": "static/img/home-selected.png"
			},
			{
				"pagePath": "pages/cart/cart",
				"text": "购物车",
				"iconPath": "static/img/cart.png",
				"selectedIconPath": "static/img/cart-selected.png"
			},
			{
				"pagePath": "pages/user/user",
				"text": "个人中心",
				"iconPath": "static/img/user.png",
				"selectedIconPath": "static/img/user-selected.png"
			}
		]
	}
	"globalStyle": {
		"navigationStyle": "custom",
		"navigationBarTextStyle": "black",
		"navigationBarTitleText": "uni-app",
		"navigationBarBackgroundColor": "#F8F8F8",
		"backgroundColor": "#F8F8F8"
	}
}
